qdetective/__init__.py
qdetective-0.1.3.dist-info/LICENSE.txt
qdetective-0.1.3.dist-info/WHEEL
qdetective-0.1.3.dist-info/METADATA
qdetective-0.1.3.dist-info/RECORD
