Metadata-Version: 2.1
Name: qdetective
Version: 0.1.3
Summary: 量化大侦探-数据通道
Author: suliang
Author-email: suliang_321@sina.com
Requires-Python: >=3.6,<4.0
Classifier: Programming Language :: Python :: 3
Classifier: Programming Language :: Python :: 3.10
Classifier: Programming Language :: Python :: 3.6
Classifier: Programming Language :: Python :: 3.7
Classifier: Programming Language :: Python :: 3.8
Classifier: Programming Language :: Python :: 3.9
